{"kRBbRgR3CARSCmF/d7sWWQ==":"mbr-1920x1275.jpg","DAu7f+rKkEeH+6DNWUB8kA==":"mbr-1920x1280.jpg","QVAz7uvJjBUFco7F1tvjHA==":"mbr-1920x1056.jpg","TN5VzUzbKdTbGEYmfYr0ow==":"mbr-1-1920x1280.jpg","k3y1MgzWdqsgEmPriQ/vVQ==":"mbr-1920x1153.jpg","vuIXLkuGt3TEp3Yei8/w8Q==":"mbr-1920x1152.jpg","onSwp4a0my0IDKN4OepgxA==":"mbr-1920x1183.jpg","J5Il7+btP4/BTOwmd8aa1g==":"mbr-2-1920x1280.jpg","bnnLwAEe8VVERhjjLiWcMA==":"mbr-1920x1080.jpg","l2kt0m3LWN5a1t38mya3sw==":"mbr-1920x1318.jpg","TYtfNsxzzh65wi929rdjrA==":"mbr-1920x1357.jpg","wW9quSFeeAobQ1P0llF1hQ==":"mbr-1920x1109.jpg","SsmEUv8CazACV7GkpKhk0A==":"mbr-1920x1388.jpg"}